samples/__init__.py
samples/classes.py
samples/num.py
samples/regex.py
py3samples_sunshine-0.0.1.dist-info/LICENSE
py3samples_sunshine-0.0.1.dist-info/METADATA
py3samples_sunshine-0.0.1.dist-info/WHEEL
py3samples_sunshine-0.0.1.dist-info/top_level.txt
py3samples_sunshine-0.0.1.dist-info/RECORD
